code_record/__init__.py
code_record/daily.py
code_record/decorators.py
code_record/mail.py
code_record/test.py
code_record/utils.py
code_record-0.1.1.dist-info/LICENSE
code_record-0.1.1.dist-info/METADATA
code_record-0.1.1.dist-info/WHEEL
code_record-0.1.1.dist-info/top_level.txt
code_record-0.1.1.dist-info/RECORD
