Metadata-Version: 2.1
Name: code-record
Version: 0.1.1
Summary: useful code records
Home-page: https://github.com/StevenLianaL/code_record
Author: Steven Wang
Author-email: wangzhou8284@outlook.com
License: UNKNOWN
Platform: UNKNOWN
Classifier: Programming Language :: Python :: 3
Classifier: License :: OSI Approved :: MIT License
